tree_plus_cli.py
tree_plus_src/__init__.py
tree_plus_src/count_tokens_lines.py
tree_plus_src/debug.py
tree_plus_src/deploy.py
tree_plus_src/engine.py
tree_plus_src/ignore.py
tree_plus_src/isabelle_symbols.py
tree_plus_src/parse_file.py
tree_plus_src/version.py
tree_plus_src/web.py
tree_plus-1.0.78.dist-info/LICENSE
tree_plus-1.0.78.dist-info/METADATA
tree_plus-1.0.78.dist-info/WHEEL
tree_plus-1.0.78.dist-info/entry_points.txt
tree_plus-1.0.78.dist-info/top_level.txt
tree_plus-1.0.78.dist-info/RECORD
