Metadata-Version: 2.2
Name: tree_plus
Version: 1.0.78
Summary: A `tree` util enhanced with tokens, lines, and components.
Author-email: Bion Howard <bion@atomiclogic.com>
Project-URL: documentation, https://github.com/bionicles/tree_plus/blob/main/README.md
Project-URL: Homepage, https://github.com/bionicles/tree_plus/blob/main/README.md
Project-URL: repository, https://www.github.com/bionicles/tree_plus
Project-URL: Issues, https://github.com/bionicles/tree_plus/issues
Keywords: tree,util,cli
Classifier: Programming Language :: Python :: 3
Classifier: Topic :: Software Development :: Libraries :: Python Modules
Classifier: License :: OSI Approved :: Apache Software License
Classifier: License :: OSI Approved :: MIT License
Classifier: Operating System :: OS Independent
Classifier: Intended Audience :: Developers
Classifier: Topic :: Utilities
Requires-Python: >=3.8
License-File: LICENSE
Requires-Dist: tiktoken
Requires-Dist: PyYAML
Requires-Dist: click
Requires-Dist: rich
Requires-Dist: tomli
Requires-Dist: natsort>=7.1
Requires-Dist: fake_useragent
Requires-Dist: bs4
Requires-Dist: func_timeout
Requires-Dist: regex
Provides-Extra: dev
Requires-Dist: pytest; extra == "dev"
Requires-Dist: pytest-dotenv; extra == "dev"
Requires-Dist: pytest-xdist; extra == "dev"
